Metadata-Version: 2.1
Name: dudb.py
Version: 0.2
Summary: RESTful Python API Wrapper to interact with the Discord Dangerous User Database at "discord.riverside.rocks"
Home-page: https://github.com/milanmdev/dudb.py
Author: Milan Mehra
License: MIT
Keywords: dudb,api,python
Platform: UNKNOWN
Classifier: Development Status :: 5 - Production/Stable
Classifier: Intended Audience :: Developers
Classifier: Topic :: Software Development :: Build Tools
Classifier: License :: OSI Approved :: MIT License
Classifier: Programming Language :: Python :: 3
Requires-Python: >=3.0
